trytond/modules/health_crypto_lab/COPYING
trytond/modules/health_crypto_lab/README.rst
trytond/modules/health_crypto_lab/__init__.py
trytond/modules/health_crypto_lab/health_crypto_lab.py
trytond/modules/health_crypto_lab/health_crypto_lab_view.xml
trytond/modules/health_crypto_lab/locale/ar.po
trytond/modules/health_crypto_lab/locale/de.po
trytond/modules/health_crypto_lab/locale/el.po
trytond/modules/health_crypto_lab/locale/eo.po
trytond/modules/health_crypto_lab/locale/es.po
trytond/modules/health_crypto_lab/locale/fr.po
trytond/modules/health_crypto_lab/locale/health_crypto_lab.pot
trytond/modules/health_crypto_lab/locale/it_IT.po
trytond/modules/health_crypto_lab/locale/ja_JP.po
trytond/modules/health_crypto_lab/locale/ka.po
trytond/modules/health_crypto_lab/locale/lo.po
trytond/modules/health_crypto_lab/locale/pt_BR.po
trytond/modules/health_crypto_lab/locale/sv.po
trytond/modules/health_crypto_lab/locale/tr.po
trytond/modules/health_crypto_lab/locale/uk.po
trytond/modules/health_crypto_lab/locale/zh_CN.po
trytond/modules/health_crypto_lab/pyproject.toml
trytond/modules/health_crypto_lab/tests/__init__.py
trytond/modules/health_crypto_lab/tests/test_health_crypto.py
trytond/modules/health_crypto_lab/tryton.cfg
trytond/modules/health_crypto_lab/view/gnuhealth_lab_form.xml
gnuhealth_crypto_lab-5.0.2.dist-info/METADATA
gnuhealth_crypto_lab-5.0.2.dist-info/WHEEL
gnuhealth_crypto_lab-5.0.2.dist-info/licenses/COPYING
gnuhealth_crypto_lab-5.0.2.dist-info/RECORD
